GMENoiseReduce/GME.py
GMENoiseReduce/__init__.py
GMENoiseReduce-0.22.dist-info/LICENSE
GMENoiseReduce-0.22.dist-info/METADATA
GMENoiseReduce-0.22.dist-info/WHEEL
GMENoiseReduce-0.22.dist-info/top_level.txt
GMENoiseReduce-0.22.dist-info/RECORD
